{"type":"FeatureCollection","features":[{"type":"Feature","geometry":{"type":"Point","coordinates":[2.43896484375,48.80686346108517]},"properties":{"name":"Lucien","description":"Cassagnes","colortext":"DeepPink"}}],"_storage":{"displayOnLoad":true,"name":"Layer 1"}}