{"type":"FeatureCollection","features":[{"type":"Feature","geometry":{"type":"Point","coordinates":[-9.77783203125,49.95121990866206]},"properties":{"_storage_options":{"iconClass":"Default"},"name":"Lucien","description":"Ca ne marche pas en fait","colortext":"DeepPink"}}],"_storage":{"displayOnLoad":true,"name":"Layer 1"}}