{"type":"FeatureCollection","features":[{"type":"Feature","geometry":{"type":"Point","coordinates":[3.0322265625,55.37911044801047]},"properties":{"titlecolor":"Magenta","titlepolice":"Arial Black","titlestyle":"italic"}}],"_storage":{"displayOnLoad":true,"name":"Layer 1"}}