{"type":"FeatureCollection","features":[{"type":"Feature","geometry":{"type":"Point","coordinates":[3.1640625,57.6689107171251]},"properties":{"name":"LOL","description":"Bonjour","colortext":"DeepPink","police":"Avantgarde","titlecolor":"Yellow"}},{"type":"Feature","geometry":{"type":"Point","coordinates":[4.68017578125,54.838663612975125]},"properties":{"name":"Mon test","colortext":"DarkBlue"}}],"_storage":{"displayOnLoad":true,"name":"Layer 1","id":19,"remoteData":{},"police":"Verdana"}}