{"type":"FeatureCollection","features":[{"type":"Feature","geometry":{"type":"Point","coordinates":[2.1533203125,48.719961222646276]},"properties":{"_storage_options":{"iconUrl":"http://www.google.fr/url?source=imglanding&ct=img&q=http://fr.fordesigner.com/imguploads/Image/cjbc/zcool/png20080526/1211810004.png&sa=X&ei=j7VLVcu6NaTdsAS7r4CYBg&ved=0CAkQ8wc&usg=AFQjCNHKDsVYe_oKxovYIupcVOx73Cmayg"},"titlecolor":"Red","titlepolice":"Arial Black","titleweight":"bold","titledecoration":"underline","name":"Leaflet","description":"Bonsoir"}},{"type":"Feature","geometry":{"type":"Point","coordinates":[2.373046875,49.46098385110948]},"properties":{"name":"lol"}}],"_storage":{"displayOnLoad":true,"name":"Layer 1","id":3}}