{"type":"FeatureCollection","features":[{"type":"Feature","geometry":{"type":"Point","coordinates":[0.32958984375,50.064191736659104]},"properties":{"_storage_options":{"iconClass":"Default"},"name":"Lucien","description":"TestTestTestTestTestTestTestTestTestTestTestTestTestTestTestTestTestTestTestTestTestTestTestTestTestTestTestTestTestTestTestTestTestTestTestTestTestTestTestTestTestTestTestTestTestTestTestTestTestTestTestTestTestTestTestTestTestTestTestTestTestTestTestTestTestTestTestTestTestTestTestTestTestTestTestTestTestTestTestTestTestTestTestTestTestTestTestTestTestTestTestTestTestTestTestTestTestTestTestTestTestTestTestTestTestTestTestTestTestTestTestTestTestTestTestTestTestTestTestTestTestTestTestTestTestTestTestTestTestTestTestTestTestTestTestTestTestTestTestTestTestTestTestTestTestTestTestTestTestTestTestTestTestTestTestTestTestTestTestTestTestTestTestTestTestTestTestTestTestTestTestTestTestTestTestTestTestTestTestTestTestTestTestTestTestTestTestTestTestTestTestTestTestTestTestTestTestTestTestTest"}}],"_storage":{"displayOnLoad":true,"name":"Layer 1"}}