{"type":"FeatureCollection","features":[{"type":"Feature","geometry":{"type":"Point","coordinates":[-4.50439453125,48.40003249610685]},"properties":{"_storage_options":{"iconUrl":"http://www.google.fr/url?source=imglanding&ct=img&q=http://fr.fordesigner.com/imguploads/Image/cjbc/zcool/png20080526/1211810004.png&sa=X&ei=qTBcVfitIMH0UIHwgKAP&ved=0CAkQ8wc&usg=AFQjCNGP7K4qcSoGlGudaUputnnogv5g1Q","iconsize":"35"},"iconsize":"25"}}],"_storage":{"displayOnLoad":true,"name":"Layer 1","id":12}}